{
  "sorted_middleware": [],
  "middleware": {
    "/": {
      "files": [
        "server/edge/chunks/_9dd07395._.js",
        "server/edge/chunks/[root-of-the-server]__de110ef0._.js",
        "server/edge/chunks/edge-wrapper_24e2925a.js"
      ],
      "name": "middleware",
      "page": "/",
      "matchers": [
        {
          "regexp": "/:nextData(_next/data/[^/]{1,})?/admin/:path*{(\\\\.json)}?",
          "originalSource": "/admin/:path*"
        },
        {
          "regexp": "/:nextData(_next/data/[^/]{1,})?/admin_dashboard/:path*{(\\\\.json)}?",
          "originalSource": "/admin_dashboard/:path*"
        }
      ],
      "wasm": [],
      "assets": [],
      "env": {
        "__NEXT_BUILD_ID": "development",
        "NEXT_SERVER_ACTIONS_ENCRYPTION_KEY": "8Paz/13Ei2RbTYvkXGT8qM7/hAot5MkDFUzlRAoXSDw=",
        "__NEXT_PREVIEW_MODE_ID": "b2bab4851925a995da9b65fe9cf39dff",
        "__NEXT_PREVIEW_MODE_ENCRYPTION_KEY": "2d189f5369eb62abc0f5c21432e896857d6a6145cd81b2dd6687287e6b329c1f",
        "__NEXT_PREVIEW_MODE_SIGNING_KEY": "00d2e06e847af20dffbe997c22d54f1d98b5e090742e890798859b3211b90bc6"
      }
    }
  },
  "instrumentation": null,
  "functions": {}
}